{
  "version": "5",
  "dialect": "mysql",
  "id": "5dbeca10-55d4-4bb6-9c48-9db25bf38740",
  "prevId": "260831c3-7447-4f83-8193-0756e9e4fbe5",
  "tables": {
    "architects": {
      "name": "architects",
      "columns": {
        "id": {
          "name": "id",
          "type": "int",
          "primaryKey": false,
          "notNull": true,
          "autoincrement": true
        },
        "architectName": {
          "name": "architectName",
          "type": "varchar(255)",
          "primaryKey": false,
          "notNull": true,
          "autoincrement": false
        },
        "architectPhone": {
          "name": "architectPhone",
          "type": "varchar(20)",
          "primaryKey": false,
          "notNull": false,
          "autoincrement": false
        },
        "architectEmail": {
          "name": "architectEmail",
          "type": "varchar(320)",
          "primaryKey": false,
          "notNull": false,
          "autoincrement": false
        },
        "architectCpfCnpj": {
          "name": "architectCpfCnpj",
          "type": "varchar(20)",
          "primaryKey": false,
          "notNull": false,
          "autoincrement": false
        },
        "architectSpecialty": {
          "name": "architectSpecialty",
          "type": "varchar(255)",
          "primaryKey": false,
          "notNull": false,
          "autoincrement": false
        },
        "architectNotes": {
          "name": "architectNotes",
          "type": "text",
          "primaryKey": false,
          "notNull": false,
          "autoincrement": false
        },
        "architectCreatedAt": {
          "name": "architectCreatedAt",
          "type": "timestamp",
          "primaryKey": false,
          "notNull": true,
          "autoincrement": false,
          "default": "(now())"
        },
        "architectUpdatedAt": {
          "name": "architectUpdatedAt",
          "type": "timestamp",
          "primaryKey": false,
          "notNull": true,
          "autoincrement": false,
          "onUpdate": true,
          "default": "(now())"
        }
      },
      "indexes": {},
      "foreignKeys": {},
      "compositePrimaryKeys": {
        "architects_id": {
          "name": "architects_id",
          "columns": [
            "id"
          ]
        }
      },
      "uniqueConstraints": {},
      "checkConstraint": {}
    },
    "business_tasks": {
      "name": "business_tasks",
      "columns": {
        "id": {
          "name": "id",
          "type": "int",
          "primaryKey": false,
          "notNull": true,
          "autoincrement": true
        },
        "negocioId": {
          "name": "negocioId",
          "type": "int",
          "primaryKey": false,
          "notNull": false,
          "autoincrement": false
        },
        "taskTitle": {
          "name": "taskTitle",
          "type": "varchar(255)",
          "primaryKey": false,
          "notNull": true,
          "autoincrement": false
        },
        "taskDescription": {
          "name": "taskDescription",
          "type": "text",
          "primaryKey": false,
          "notNull": false,
          "autoincrement": false
        },
        "taskDueDate": {
          "name": "taskDueDate",
          "type": "date",
          "primaryKey": false,
          "notNull": true,
          "autoincrement": false
        },
        "taskPriority": {
          "name": "taskPriority",
          "type": "enum('normal','urgente')",
          "primaryKey": false,
          "notNull": true,
          "autoincrement": false,
          "default": "'normal'"
        },
        "taskIsCompleted": {
          "name": "taskIsCompleted",
          "type": "boolean",
          "primaryKey": false,
          "notNull": false,
          "autoincrement": false,
          "default": false
        },
        "taskCompletedAt": {
          "name": "taskCompletedAt",
          "type": "timestamp",
          "primaryKey": false,
          "notNull": false,
          "autoincrement": false
        },
        "taskCreatedAt": {
          "name": "taskCreatedAt",
          "type": "timestamp",
          "primaryKey": false,
          "notNull": true,
          "autoincrement": false,
          "default": "(now())"
        }
      },
      "indexes": {},
      "foreignKeys": {},
      "compositePrimaryKeys": {
        "business_tasks_id": {
          "name": "business_tasks_id",
          "columns": [
            "id"
          ]
        }
      },
      "uniqueConstraints": {},
      "checkConstraint": {}
    },
    "calendar_events": {
      "name": "calendar_events",
      "columns": {
        "id": {
          "name": "id",
          "type": "int",
          "primaryKey": false,
          "notNull": true,
          "autoincrement": true
        },
        "title": {
          "name": "title",
          "type": "varchar(255)",
          "primaryKey": false,
          "notNull": true,
          "autoincrement": false
        },
        "description": {
          "name": "description",
          "type": "text",
          "primaryKey": false,
          "notNull": false,
          "autoincrement": false
        },
        "eventDate": {
          "name": "eventDate",
          "type": "date",
          "primaryKey": false,
          "notNull": true,
          "autoincrement": false
        },
        "eventType": {
          "name": "eventType",
          "type": "enum('vencimento_contrato','renovacao_licenca','manutencao','marco_projeto','reuniao','outro')",
          "primaryKey": false,
          "notNull": true,
          "autoincrement": false
        },
        "relatedEntity": {
          "name": "relatedEntity",
          "type": "varchar(128)",
          "primaryKey": false,
          "notNull": false,
          "autoincrement": false
        },
        "relatedEntityId": {
          "name": "relatedEntityId",
          "type": "int",
          "primaryKey": false,
          "notNull": false,
          "autoincrement": false
        },
        "alertDaysBefore": {
          "name": "alertDaysBefore",
          "type": "int",
          "primaryKey": false,
          "notNull": false,
          "autoincrement": false,
          "default": 7
        },
        "isCompleted": {
          "name": "isCompleted",
          "type": "boolean",
          "primaryKey": false,
          "notNull": false,
          "autoincrement": false,
          "default": false
        },
        "createdAt": {
          "name": "createdAt",
          "type": "timestamp",
          "primaryKey": false,
          "notNull": true,
          "autoincrement": false,
          "default": "(now())"
        }
      },
      "indexes": {},
      "foreignKeys": {},
      "compositePrimaryKeys": {
        "calendar_events_id": {
          "name": "calendar_events_id",
          "columns": [
            "id"
          ]
        }
      },
      "uniqueConstraints": {},
      "checkConstraint": {}
    },
    "captadores": {
      "name": "captadores",
      "columns": {
        "id": {
          "name": "id",
          "type": "int",
          "primaryKey": false,
          "notNull": true,
          "autoincrement": true
        },
        "name": {
          "name": "name",
          "type": "varchar(255)",
          "primaryKey": false,
          "notNull": true,
          "autoincrement": false
        },
        "partnerType": {
          "name": "partnerType",
          "type": "enum('corretor','advogado','investidor','permutario','outros')",
          "primaryKey": false,
          "notNull": true,
          "autoincrement": false,
          "default": "'corretor'"
        },
        "phone": {
          "name": "phone",
          "type": "varchar(20)",
          "primaryKey": false,
          "notNull": false,
          "autoincrement": false
        },
        "email": {
          "name": "email",
          "type": "varchar(320)",
          "primaryKey": false,
          "notNull": false,
          "autoincrement": false
        },
        "cpfCnpj": {
          "name": "cpfCnpj",
          "type": "varchar(20)",
          "primaryKey": false,
          "notNull": false,
          "autoincrement": false
        },
        "defaultCommission": {
          "name": "defaultCommission",
          "type": "decimal(5,2)",
          "primaryKey": false,
          "notNull": false,
          "autoincrement": false,
          "default": "'5.00'"
        },
        "notes": {
          "name": "notes",
          "type": "text",
          "primaryKey": false,
          "notNull": false,
          "autoincrement": false
        },
        "createdAt": {
          "name": "createdAt",
          "type": "timestamp",
          "primaryKey": false,
          "notNull": true,
          "autoincrement": false,
          "default": "(now())"
        },
        "updatedAt": {
          "name": "updatedAt",
          "type": "timestamp",
          "primaryKey": false,
          "notNull": true,
          "autoincrement": false,
          "onUpdate": true,
          "default": "(now())"
        }
      },
      "indexes": {},
      "foreignKeys": {},
      "compositePrimaryKeys": {
        "captadores_id": {
          "name": "captadores_id",
          "columns": [
            "id"
          ]
        }
      },
      "uniqueConstraints": {},
      "checkConstraint": {}
    },
    "clients": {
      "name": "clients",
      "columns": {
        "id": {
          "name": "id",
          "type": "int",
          "primaryKey": false,
          "notNull": true,
          "autoincrement": true
        },
        "name": {
          "name": "name",
          "type": "varchar(255)",
          "primaryKey": false,
          "notNull": true,
          "autoincrement": false
        },
        "cpfCnpj": {
          "name": "cpfCnpj",
          "type": "varchar(20)",
          "primaryKey": false,
          "notNull": false,
          "autoincrement": false
        },
        "email": {
          "name": "email",
          "type": "varchar(320)",
          "primaryKey": false,
          "notNull": false,
          "autoincrement": false
        },
        "phone": {
          "name": "phone",
          "type": "varchar(20)",
          "primaryKey": false,
          "notNull": false,
          "autoincrement": false
        },
        "phone2": {
          "name": "phone2",
          "type": "varchar(20)",
          "primaryKey": false,
          "notNull": false,
          "autoincrement": false
        },
        "address": {
          "name": "address",
          "type": "text",
          "primaryKey": false,
          "notNull": false,
          "autoincrement": false
        },
        "notes": {
          "name": "notes",
          "type": "text",
          "primaryKey": false,
          "notNull": false,
          "autoincrement": false
        },
        "createdAt": {
          "name": "createdAt",
          "type": "timestamp",
          "primaryKey": false,
          "notNull": true,
          "autoincrement": false,
          "default": "(now())"
        },
        "updatedAt": {
          "name": "updatedAt",
          "type": "timestamp",
          "primaryKey": false,
          "notNull": true,
          "autoincrement": false,
          "onUpdate": true,
          "default": "(now())"
        }
      },
      "indexes": {},
      "foreignKeys": {},
      "compositePrimaryKeys": {
        "clients_id": {
          "name": "clients_id",
          "columns": [
            "id"
          ]
        }
      },
      "uniqueConstraints": {},
      "checkConstraint": {}
    },
    "construction_images": {
      "name": "construction_images",
      "columns": {
        "id": {
          "name": "id",
          "type": "int",
          "primaryKey": false,
          "notNull": true,
          "autoincrement": true
        },
        "imageConstructionId": {
          "name": "imageConstructionId",
          "type": "int",
          "primaryKey": false,
          "notNull": true,
          "autoincrement": false
        },
        "imageUrl": {
          "name": "imageUrl",
          "type": "text",
          "primaryKey": false,
          "notNull": true,
          "autoincrement": false
        },
        "imageKey": {
          "name": "imageKey",
          "type": "varchar(512)",
          "primaryKey": false,
          "notNull": false,
          "autoincrement": false
        },
        "imageCaption": {
          "name": "imageCaption",
          "type": "varchar(255)",
          "primaryKey": false,
          "notNull": false,
          "autoincrement": false
        },
        "imageUploadedBy": {
          "name": "imageUploadedBy",
          "type": "varchar(255)",
          "primaryKey": false,
          "notNull": false,
          "autoincrement": false
        },
        "imageUploadedAt": {
          "name": "imageUploadedAt",
          "type": "timestamp",
          "primaryKey": false,
          "notNull": true,
          "autoincrement": false,
          "default": "(now())"
        }
      },
      "indexes": {},
      "foreignKeys": {},
      "compositePrimaryKeys": {
        "construction_images_id": {
          "name": "construction_images_id",
          "columns": [
            "id"
          ]
        }
      },
      "uniqueConstraints": {},
      "checkConstraint": {}
    },
    "construction_reports": {
      "name": "construction_reports",
      "columns": {
        "id": {
          "name": "id",
          "type": "int",
          "primaryKey": false,
          "notNull": true,
          "autoincrement": true
        },
        "reportConstructionId": {
          "name": "reportConstructionId",
          "type": "int",
          "primaryKey": false,
          "notNull": true,
          "autoincrement": false
        },
        "reportTitle": {
          "name": "reportTitle",
          "type": "varchar(255)",
          "primaryKey": false,
          "notNull": true,
          "autoincrement": false
        },
        "reportContent": {
          "name": "reportContent",
          "type": "text",
          "primaryKey": false,
          "notNull": true,
          "autoincrement": false
        },
        "reportAuthor": {
          "name": "reportAuthor",
          "type": "varchar(255)",
          "primaryKey": false,
          "notNull": false,
          "autoincrement": false
        },
        "reportDate": {
          "name": "reportDate",
          "type": "date",
          "primaryKey": false,
          "notNull": true,
          "autoincrement": false
        },
        "reportCreatedAt": {
          "name": "reportCreatedAt",
          "type": "timestamp",
          "primaryKey": false,
          "notNull": true,
          "autoincrement": false,
          "default": "(now())"
        },
        "reportUpdatedAt": {
          "name": "reportUpdatedAt",
          "type": "timestamp",
          "primaryKey": false,
          "notNull": true,
          "autoincrement": false,
          "onUpdate": true,
          "default": "(now())"
        }
      },
      "indexes": {},
      "foreignKeys": {},
      "compositePrimaryKeys": {
        "construction_reports_id": {
          "name": "construction_reports_id",
          "columns": [
            "id"
          ]
        }
      },
      "uniqueConstraints": {},
      "checkConstraint": {}
    },
    "construction_tasks": {
      "name": "construction_tasks",
      "columns": {
        "id": {
          "name": "id",
          "type": "int",
          "primaryKey": false,
          "notNull": true,
          "autoincrement": true
        },
        "taskConstructionId": {
          "name": "taskConstructionId",
          "type": "int",
          "primaryKey": false,
          "notNull": false,
          "autoincrement": false
        },
        "cTaskTitle": {
          "name": "cTaskTitle",
          "type": "varchar(255)",
          "primaryKey": false,
          "notNull": true,
          "autoincrement": false
        },
        "cTaskDescription": {
          "name": "cTaskDescription",
          "type": "text",
          "primaryKey": false,
          "notNull": false,
          "autoincrement": false
        },
        "cTaskDueDate": {
          "name": "cTaskDueDate",
          "type": "date",
          "primaryKey": false,
          "notNull": true,
          "autoincrement": false
        },
        "cTaskType": {
          "name": "cTaskType",
          "type": "enum('marco','prazo_entrega','vistoria','reuniao','outro')",
          "primaryKey": false,
          "notNull": true,
          "autoincrement": false,
          "default": "'outro'"
        },
        "cTaskIsCompleted": {
          "name": "cTaskIsCompleted",
          "type": "boolean",
          "primaryKey": false,
          "notNull": false,
          "autoincrement": false,
          "default": false
        },
        "cTaskCompletedAt": {
          "name": "cTaskCompletedAt",
          "type": "timestamp",
          "primaryKey": false,
          "notNull": false,
          "autoincrement": false
        },
        "cTaskCreatedAt": {
          "name": "cTaskCreatedAt",
          "type": "timestamp",
          "primaryKey": false,
          "notNull": true,
          "autoincrement": false,
          "default": "(now())"
        }
      },
      "indexes": {},
      "foreignKeys": {},
      "compositePrimaryKeys": {
        "construction_tasks_id": {
          "name": "construction_tasks_id",
          "columns": [
            "id"
          ]
        }
      },
      "uniqueConstraints": {},
      "checkConstraint": {}
    },
    "constructions": {
      "name": "constructions",
      "columns": {
        "id": {
          "name": "id",
          "type": "int",
          "primaryKey": false,
          "notNull": true,
          "autoincrement": true
        },
        "constructionTitle": {
          "name": "constructionTitle",
          "type": "varchar(255)",
          "primaryKey": false,
          "notNull": true,
          "autoincrement": false
        },
        "constructionAddress": {
          "name": "constructionAddress",
          "type": "text",
          "primaryKey": false,
          "notNull": false,
          "autoincrement": false
        },
        "constructionCity": {
          "name": "constructionCity",
          "type": "varchar(128)",
          "primaryKey": false,
          "notNull": false,
          "autoincrement": false
        },
        "constructionState": {
          "name": "constructionState",
          "type": "varchar(2)",
          "primaryKey": false,
          "notNull": false,
          "autoincrement": false
        },
        "hasKey": {
          "name": "hasKey",
          "type": "boolean",
          "primaryKey": false,
          "notNull": false,
          "autoincrement": false,
          "default": false
        },
        "contractorId": {
          "name": "contractorId",
          "type": "int",
          "primaryKey": false,
          "notNull": false,
          "autoincrement": false
        },
        "architectId": {
          "name": "architectId",
          "type": "int",
          "primaryKey": false,
          "notNull": false,
          "autoincrement": false
        },
        "constructionType": {
          "name": "constructionType",
          "type": "enum('residencial','comercial','reforma','galpao','loteamento','outro')",
          "primaryKey": false,
          "notNull": true,
          "autoincrement": false,
          "default": "'residencial'"
        },
        "constructionStatus": {
          "name": "constructionStatus",
          "type": "enum('em_andamento','paralisada','concluida')",
          "primaryKey": false,
          "notNull": true,
          "autoincrement": false,
          "default": "'em_andamento'"
        },
        "constructionProgress": {
          "name": "constructionProgress",
          "type": "enum('avancada','em_dia','atrasada','totalmente_atrasada')",
          "primaryKey": false,
          "notNull": true,
          "autoincrement": false,
          "default": "'em_dia'"
        },
        "constructionDescription": {
          "name": "constructionDescription",
          "type": "text",
          "primaryKey": false,
          "notNull": false,
          "autoincrement": false
        },
        "constructionIsArchived": {
          "name": "constructionIsArchived",
          "type": "boolean",
          "primaryKey": false,
          "notNull": false,
          "autoincrement": false,
          "default": false
        },
        "constructionStartDate": {
          "name": "constructionStartDate",
          "type": "date",
          "primaryKey": false,
          "notNull": false,
          "autoincrement": false
        },
        "constructionExpectedEndDate": {
          "name": "constructionExpectedEndDate",
          "type": "date",
          "primaryKey": false,
          "notNull": false,
          "autoincrement": false
        },
        "constructionCreatedAt": {
          "name": "constructionCreatedAt",
          "type": "timestamp",
          "primaryKey": false,
          "notNull": true,
          "autoincrement": false,
          "default": "(now())"
        },
        "constructionUpdatedAt": {
          "name": "constructionUpdatedAt",
          "type": "timestamp",
          "primaryKey": false,
          "notNull": true,
          "autoincrement": false,
          "onUpdate": true,
          "default": "(now())"
        }
      },
      "indexes": {},
      "foreignKeys": {},
      "compositePrimaryKeys": {
        "constructions_id": {
          "name": "constructions_id",
          "columns": [
            "id"
          ]
        }
      },
      "uniqueConstraints": {},
      "checkConstraint": {}
    },
    "contractors": {
      "name": "contractors",
      "columns": {
        "id": {
          "name": "id",
          "type": "int",
          "primaryKey": false,
          "notNull": true,
          "autoincrement": true
        },
        "name": {
          "name": "name",
          "type": "varchar(255)",
          "primaryKey": false,
          "notNull": true,
          "autoincrement": false
        },
        "contractorPhone": {
          "name": "contractorPhone",
          "type": "varchar(20)",
          "primaryKey": false,
          "notNull": false,
          "autoincrement": false
        },
        "contractorEmail": {
          "name": "contractorEmail",
          "type": "varchar(320)",
          "primaryKey": false,
          "notNull": false,
          "autoincrement": false
        },
        "contractorCpfCnpj": {
          "name": "contractorCpfCnpj",
          "type": "varchar(20)",
          "primaryKey": false,
          "notNull": false,
          "autoincrement": false
        },
        "contractorSpecialty": {
          "name": "contractorSpecialty",
          "type": "varchar(255)",
          "primaryKey": false,
          "notNull": false,
          "autoincrement": false
        },
        "contractorNotes": {
          "name": "contractorNotes",
          "type": "text",
          "primaryKey": false,
          "notNull": false,
          "autoincrement": false
        },
        "contractorCreatedAt": {
          "name": "contractorCreatedAt",
          "type": "timestamp",
          "primaryKey": false,
          "notNull": true,
          "autoincrement": false,
          "default": "(now())"
        },
        "contractorUpdatedAt": {
          "name": "contractorUpdatedAt",
          "type": "timestamp",
          "primaryKey": false,
          "notNull": true,
          "autoincrement": false,
          "onUpdate": true,
          "default": "(now())"
        }
      },
      "indexes": {},
      "foreignKeys": {},
      "compositePrimaryKeys": {
        "contractors_id": {
          "name": "contractors_id",
          "columns": [
            "id"
          ]
        }
      },
      "uniqueConstraints": {},
      "checkConstraint": {}
    },
    "documents": {
      "name": "documents",
      "columns": {
        "id": {
          "name": "id",
          "type": "int",
          "primaryKey": false,
          "notNull": true,
          "autoincrement": true
        },
        "title": {
          "name": "title",
          "type": "varchar(255)",
          "primaryKey": false,
          "notNull": true,
          "autoincrement": false
        },
        "category": {
          "name": "category",
          "type": "enum('contrato','alvara','certidao','planta','foto','fatura','recibo','outro')",
          "primaryKey": false,
          "notNull": true,
          "autoincrement": false
        },
        "description": {
          "name": "description",
          "type": "text",
          "primaryKey": false,
          "notNull": false,
          "autoincrement": false
        },
        "fileUrl": {
          "name": "fileUrl",
          "type": "text",
          "primaryKey": false,
          "notNull": false,
          "autoincrement": false
        },
        "fileKey": {
          "name": "fileKey",
          "type": "varchar(512)",
          "primaryKey": false,
          "notNull": false,
          "autoincrement": false
        },
        "fileName": {
          "name": "fileName",
          "type": "varchar(255)",
          "primaryKey": false,
          "notNull": false,
          "autoincrement": false
        },
        "mimeType": {
          "name": "mimeType",
          "type": "varchar(128)",
          "primaryKey": false,
          "notNull": false,
          "autoincrement": false
        },
        "expiryDate": {
          "name": "expiryDate",
          "type": "date",
          "primaryKey": false,
          "notNull": false,
          "autoincrement": false
        },
        "relatedEntity": {
          "name": "relatedEntity",
          "type": "varchar(128)",
          "primaryKey": false,
          "notNull": false,
          "autoincrement": false
        },
        "relatedEntityId": {
          "name": "relatedEntityId",
          "type": "int",
          "primaryKey": false,
          "notNull": false,
          "autoincrement": false
        },
        "uploadedBy": {
          "name": "uploadedBy",
          "type": "int",
          "primaryKey": false,
          "notNull": false,
          "autoincrement": false
        },
        "createdAt": {
          "name": "createdAt",
          "type": "timestamp",
          "primaryKey": false,
          "notNull": true,
          "autoincrement": false,
          "default": "(now())"
        },
        "updatedAt": {
          "name": "updatedAt",
          "type": "timestamp",
          "primaryKey": false,
          "notNull": true,
          "autoincrement": false,
          "onUpdate": true,
          "default": "(now())"
        }
      },
      "indexes": {},
      "foreignKeys": {},
      "compositePrimaryKeys": {
        "documents_id": {
          "name": "documents_id",
          "columns": [
            "id"
          ]
        }
      },
      "uniqueConstraints": {},
      "checkConstraint": {}
    },
    "employees": {
      "name": "employees",
      "columns": {
        "id": {
          "name": "id",
          "type": "int",
          "primaryKey": false,
          "notNull": true,
          "autoincrement": true
        },
        "name": {
          "name": "name",
          "type": "varchar(255)",
          "primaryKey": false,
          "notNull": true,
          "autoincrement": false
        },
        "cpf": {
          "name": "cpf",
          "type": "varchar(14)",
          "primaryKey": false,
          "notNull": false,
          "autoincrement": false
        },
        "email": {
          "name": "email",
          "type": "varchar(320)",
          "primaryKey": false,
          "notNull": false,
          "autoincrement": false
        },
        "phone": {
          "name": "phone",
          "type": "varchar(20)",
          "primaryKey": false,
          "notNull": false,
          "autoincrement": false
        },
        "position": {
          "name": "position",
          "type": "varchar(128)",
          "primaryKey": false,
          "notNull": false,
          "autoincrement": false
        },
        "department": {
          "name": "department",
          "type": "varchar(128)",
          "primaryKey": false,
          "notNull": false,
          "autoincrement": false
        },
        "salary": {
          "name": "salary",
          "type": "decimal(12,2)",
          "primaryKey": false,
          "notNull": false,
          "autoincrement": false
        },
        "hireDate": {
          "name": "hireDate",
          "type": "date",
          "primaryKey": false,
          "notNull": false,
          "autoincrement": false
        },
        "status": {
          "name": "status",
          "type": "enum('ativo','ferias','afastado','desligado')",
          "primaryKey": false,
          "notNull": true,
          "autoincrement": false,
          "default": "'ativo'"
        },
        "projectAllocation": {
          "name": "projectAllocation",
          "type": "varchar(255)",
          "primaryKey": false,
          "notNull": false,
          "autoincrement": false
        },
        "notes": {
          "name": "notes",
          "type": "text",
          "primaryKey": false,
          "notNull": false,
          "autoincrement": false
        },
        "createdAt": {
          "name": "createdAt",
          "type": "timestamp",
          "primaryKey": false,
          "notNull": true,
          "autoincrement": false,
          "default": "(now())"
        },
        "updatedAt": {
          "name": "updatedAt",
          "type": "timestamp",
          "primaryKey": false,
          "notNull": true,
          "autoincrement": false,
          "onUpdate": true,
          "default": "(now())"
        }
      },
      "indexes": {},
      "foreignKeys": {},
      "compositePrimaryKeys": {
        "employees_id": {
          "name": "employees_id",
          "columns": [
            "id"
          ]
        }
      },
      "uniqueConstraints": {},
      "checkConstraint": {}
    },
    "fleet": {
      "name": "fleet",
      "columns": {
        "id": {
          "name": "id",
          "type": "int",
          "primaryKey": false,
          "notNull": true,
          "autoincrement": true
        },
        "plate": {
          "name": "plate",
          "type": "varchar(10)",
          "primaryKey": false,
          "notNull": true,
          "autoincrement": false
        },
        "model": {
          "name": "model",
          "type": "varchar(128)",
          "primaryKey": false,
          "notNull": true,
          "autoincrement": false
        },
        "year": {
          "name": "year",
          "type": "int",
          "primaryKey": false,
          "notNull": false,
          "autoincrement": false
        },
        "status": {
          "name": "status",
          "type": "enum('disponivel','em_uso','manutencao','inativo')",
          "primaryKey": false,
          "notNull": true,
          "autoincrement": false,
          "default": "'disponivel'"
        },
        "assignedTo": {
          "name": "assignedTo",
          "type": "varchar(255)",
          "primaryKey": false,
          "notNull": false,
          "autoincrement": false
        },
        "nextMaintenanceDate": {
          "name": "nextMaintenanceDate",
          "type": "date",
          "primaryKey": false,
          "notNull": false,
          "autoincrement": false
        },
        "km": {
          "name": "km",
          "type": "int",
          "primaryKey": false,
          "notNull": false,
          "autoincrement": false
        },
        "notes": {
          "name": "notes",
          "type": "text",
          "primaryKey": false,
          "notNull": false,
          "autoincrement": false
        },
        "createdAt": {
          "name": "createdAt",
          "type": "timestamp",
          "primaryKey": false,
          "notNull": true,
          "autoincrement": false,
          "default": "(now())"
        },
        "updatedAt": {
          "name": "updatedAt",
          "type": "timestamp",
          "primaryKey": false,
          "notNull": true,
          "autoincrement": false,
          "onUpdate": true,
          "default": "(now())"
        }
      },
      "indexes": {},
      "foreignKeys": {},
      "compositePrimaryKeys": {
        "fleet_id": {
          "name": "fleet_id",
          "columns": [
            "id"
          ]
        }
      },
      "uniqueConstraints": {},
      "checkConstraint": {}
    },
    "negocios": {
      "name": "negocios",
      "columns": {
        "id": {
          "name": "id",
          "type": "int",
          "primaryKey": false,
          "notNull": true,
          "autoincrement": true
        },
        "title": {
          "name": "title",
          "type": "varchar(255)",
          "primaryKey": false,
          "notNull": true,
          "autoincrement": false
        },
        "negOwnership": {
          "name": "negOwnership",
          "type": "enum('proprio','terceiros')",
          "primaryKey": false,
          "notNull": true,
          "autoincrement": false,
          "default": "'proprio'"
        },
        "captadorId": {
          "name": "captadorId",
          "type": "int",
          "primaryKey": false,
          "notNull": false,
          "autoincrement": false
        },
        "address": {
          "name": "address",
          "type": "text",
          "primaryKey": false,
          "notNull": false,
          "autoincrement": false
        },
        "negCity": {
          "name": "negCity",
          "type": "varchar(128)",
          "primaryKey": false,
          "notNull": false,
          "autoincrement": false
        },
        "negState": {
          "name": "negState",
          "type": "varchar(2)",
          "primaryKey": false,
          "notNull": false,
          "autoincrement": false
        },
        "phase": {
          "name": "phase",
          "type": "enum('prospeccao','analise','negociacao','due_diligence','aprovado','fechado','cancelado')",
          "primaryKey": false,
          "notNull": true,
          "autoincrement": false,
          "default": "'prospeccao'"
        },
        "operationType": {
          "name": "operationType",
          "type": "enum('compra','venda','permuta','incorporacao','loteamento','reforma','outro')",
          "primaryKey": false,
          "notNull": true,
          "autoincrement": false,
          "default": "'compra'"
        },
        "negPriority": {
          "name": "negPriority",
          "type": "enum('baixa','media','alta','urgente')",
          "primaryKey": false,
          "notNull": true,
          "autoincrement": false,
          "default": "'media'"
        },
        "totalArea": {
          "name": "totalArea",
          "type": "decimal(12,2)",
          "primaryKey": false,
          "notNull": false,
          "autoincrement": false
        },
        "usableArea": {
          "name": "usableArea",
          "type": "decimal(12,2)",
          "primaryKey": false,
          "notNull": false,
          "autoincrement": false
        },
        "zoning": {
          "name": "zoning",
          "type": "varchar(128)",
          "primaryKey": false,
          "notNull": false,
          "autoincrement": false
        },
        "constructivePotential": {
          "name": "constructivePotential",
          "type": "decimal(8,2)",
          "primaryKey": false,
          "notNull": false,
          "autoincrement": false
        },
        "opportunityCost": {
          "name": "opportunityCost",
          "type": "decimal(14,2)",
          "primaryKey": false,
          "notNull": false,
          "autoincrement": false
        },
        "marketValue": {
          "name": "marketValue",
          "type": "decimal(14,2)",
          "primaryKey": false,
          "notNull": false,
          "autoincrement": false
        },
        "maxInvestment": {
          "name": "maxInvestment",
          "type": "decimal(14,2)",
          "primaryKey": false,
          "notNull": false,
          "autoincrement": false
        },
        "estimatedVGV": {
          "name": "estimatedVGV",
          "type": "decimal(14,2)",
          "primaryKey": false,
          "notNull": false,
          "autoincrement": false
        },
        "tirPercent": {
          "name": "tirPercent",
          "type": "decimal(8,2)",
          "primaryKey": false,
          "notNull": false,
          "autoincrement": false
        },
        "profitMarginPercent": {
          "name": "profitMarginPercent",
          "type": "decimal(8,2)",
          "primaryKey": false,
          "notNull": false,
          "autoincrement": false
        },
        "documentationStatus": {
          "name": "documentationStatus",
          "type": "text",
          "primaryKey": false,
          "notNull": false,
          "autoincrement": false
        },
        "nextAction": {
          "name": "nextAction",
          "type": "text",
          "primaryKey": false,
          "notNull": false,
          "autoincrement": false
        },
        "nextActionPriority": {
          "name": "nextActionPriority",
          "type": "enum('normal','urgente')",
          "primaryKey": false,
          "notNull": false,
          "autoincrement": false,
          "default": "'normal'"
        },
        "nextActionDate": {
          "name": "nextActionDate",
          "type": "date",
          "primaryKey": false,
          "notNull": false,
          "autoincrement": false
        },
        "isArchived": {
          "name": "isArchived",
          "type": "boolean",
          "primaryKey": false,
          "notNull": false,
          "autoincrement": false,
          "default": false
        },
        "negNotes": {
          "name": "negNotes",
          "type": "text",
          "primaryKey": false,
          "notNull": false,
          "autoincrement": false
        },
        "createdAt": {
          "name": "createdAt",
          "type": "timestamp",
          "primaryKey": false,
          "notNull": true,
          "autoincrement": false,
          "default": "(now())"
        },
        "updatedAt": {
          "name": "updatedAt",
          "type": "timestamp",
          "primaryKey": false,
          "notNull": true,
          "autoincrement": false,
          "onUpdate": true,
          "default": "(now())"
        }
      },
      "indexes": {},
      "foreignKeys": {},
      "compositePrimaryKeys": {
        "negocios_id": {
          "name": "negocios_id",
          "columns": [
            "id"
          ]
        }
      },
      "uniqueConstraints": {},
      "checkConstraint": {}
    },
    "owners": {
      "name": "owners",
      "columns": {
        "id": {
          "name": "id",
          "type": "int",
          "primaryKey": false,
          "notNull": true,
          "autoincrement": true
        },
        "name": {
          "name": "name",
          "type": "varchar(255)",
          "primaryKey": false,
          "notNull": true,
          "autoincrement": false
        },
        "cpfCnpj": {
          "name": "cpfCnpj",
          "type": "varchar(20)",
          "primaryKey": false,
          "notNull": false,
          "autoincrement": false
        },
        "email": {
          "name": "email",
          "type": "varchar(320)",
          "primaryKey": false,
          "notNull": false,
          "autoincrement": false
        },
        "phone": {
          "name": "phone",
          "type": "varchar(20)",
          "primaryKey": false,
          "notNull": false,
          "autoincrement": false
        },
        "phone2": {
          "name": "phone2",
          "type": "varchar(20)",
          "primaryKey": false,
          "notNull": false,
          "autoincrement": false
        },
        "address": {
          "name": "address",
          "type": "text",
          "primaryKey": false,
          "notNull": false,
          "autoincrement": false
        },
        "bankName": {
          "name": "bankName",
          "type": "varchar(128)",
          "primaryKey": false,
          "notNull": false,
          "autoincrement": false
        },
        "bankAgency": {
          "name": "bankAgency",
          "type": "varchar(20)",
          "primaryKey": false,
          "notNull": false,
          "autoincrement": false
        },
        "bankAccount": {
          "name": "bankAccount",
          "type": "varchar(30)",
          "primaryKey": false,
          "notNull": false,
          "autoincrement": false
        },
        "pixKey": {
          "name": "pixKey",
          "type": "varchar(255)",
          "primaryKey": false,
          "notNull": false,
          "autoincrement": false
        },
        "notes": {
          "name": "notes",
          "type": "text",
          "primaryKey": false,
          "notNull": false,
          "autoincrement": false
        },
        "createdAt": {
          "name": "createdAt",
          "type": "timestamp",
          "primaryKey": false,
          "notNull": true,
          "autoincrement": false,
          "default": "(now())"
        },
        "updatedAt": {
          "name": "updatedAt",
          "type": "timestamp",
          "primaryKey": false,
          "notNull": true,
          "autoincrement": false,
          "onUpdate": true,
          "default": "(now())"
        }
      },
      "indexes": {},
      "foreignKeys": {},
      "compositePrimaryKeys": {
        "owners_id": {
          "name": "owners_id",
          "columns": [
            "id"
          ]
        }
      },
      "uniqueConstraints": {},
      "checkConstraint": {}
    },
    "petty_cash": {
      "name": "petty_cash",
      "columns": {
        "id": {
          "name": "id",
          "type": "int",
          "primaryKey": false,
          "notNull": true,
          "autoincrement": true
        },
        "description": {
          "name": "description",
          "type": "varchar(255)",
          "primaryKey": false,
          "notNull": true,
          "autoincrement": false
        },
        "amount": {
          "name": "amount",
          "type": "decimal(10,2)",
          "primaryKey": false,
          "notNull": true,
          "autoincrement": false
        },
        "type": {
          "name": "type",
          "type": "enum('entrada','saida')",
          "primaryKey": false,
          "notNull": true,
          "autoincrement": false
        },
        "category": {
          "name": "category",
          "type": "varchar(128)",
          "primaryKey": false,
          "notNull": false,
          "autoincrement": false
        },
        "date": {
          "name": "date",
          "type": "date",
          "primaryKey": false,
          "notNull": true,
          "autoincrement": false
        },
        "receiptUrl": {
          "name": "receiptUrl",
          "type": "text",
          "primaryKey": false,
          "notNull": false,
          "autoincrement": false
        },
        "receiptKey": {
          "name": "receiptKey",
          "type": "varchar(512)",
          "primaryKey": false,
          "notNull": false,
          "autoincrement": false
        },
        "registeredBy": {
          "name": "registeredBy",
          "type": "int",
          "primaryKey": false,
          "notNull": false,
          "autoincrement": false
        },
        "createdAt": {
          "name": "createdAt",
          "type": "timestamp",
          "primaryKey": false,
          "notNull": true,
          "autoincrement": false,
          "default": "(now())"
        }
      },
      "indexes": {},
      "foreignKeys": {},
      "compositePrimaryKeys": {
        "petty_cash_id": {
          "name": "petty_cash_id",
          "columns": [
            "id"
          ]
        }
      },
      "uniqueConstraints": {},
      "checkConstraint": {}
    },
    "properties": {
      "name": "properties",
      "columns": {
        "id": {
          "name": "id",
          "type": "int",
          "primaryKey": false,
          "notNull": true,
          "autoincrement": true
        },
        "code": {
          "name": "code",
          "type": "varchar(20)",
          "primaryKey": false,
          "notNull": false,
          "autoincrement": false
        },
        "title": {
          "name": "title",
          "type": "varchar(255)",
          "primaryKey": false,
          "notNull": true,
          "autoincrement": false
        },
        "ownership": {
          "name": "ownership",
          "type": "enum('domobianca','terceiros')",
          "primaryKey": false,
          "notNull": true,
          "autoincrement": false,
          "default": "'domobianca'"
        },
        "propertyType": {
          "name": "propertyType",
          "type": "enum('residencial','apartamento','galpao','sala_comercial','lote','casa','cobertura','kitnet','outro')",
          "primaryKey": false,
          "notNull": true,
          "autoincrement": false,
          "default": "'residencial'"
        },
        "status": {
          "name": "status",
          "type": "enum('disponivel_locacao','disponivel_venda','alugado','vendido','arquivado')",
          "primaryKey": false,
          "notNull": true,
          "autoincrement": false,
          "default": "'disponivel_locacao'"
        },
        "ownerId": {
          "name": "ownerId",
          "type": "int",
          "primaryKey": false,
          "notNull": false,
          "autoincrement": false
        },
        "street": {
          "name": "street",
          "type": "varchar(255)",
          "primaryKey": false,
          "notNull": false,
          "autoincrement": false
        },
        "number": {
          "name": "number",
          "type": "varchar(20)",
          "primaryKey": false,
          "notNull": false,
          "autoincrement": false
        },
        "complement": {
          "name": "complement",
          "type": "varchar(128)",
          "primaryKey": false,
          "notNull": false,
          "autoincrement": false
        },
        "neighborhood": {
          "name": "neighborhood",
          "type": "varchar(128)",
          "primaryKey": false,
          "notNull": false,
          "autoincrement": false
        },
        "city": {
          "name": "city",
          "type": "varchar(128)",
          "primaryKey": false,
          "notNull": false,
          "autoincrement": false
        },
        "state": {
          "name": "state",
          "type": "varchar(2)",
          "primaryKey": false,
          "notNull": false,
          "autoincrement": false
        },
        "zipCode": {
          "name": "zipCode",
          "type": "varchar(10)",
          "primaryKey": false,
          "notNull": false,
          "autoincrement": false
        },
        "area": {
          "name": "area",
          "type": "decimal(10,2)",
          "primaryKey": false,
          "notNull": false,
          "autoincrement": false
        },
        "bedrooms": {
          "name": "bedrooms",
          "type": "int",
          "primaryKey": false,
          "notNull": false,
          "autoincrement": false
        },
        "bathrooms": {
          "name": "bathrooms",
          "type": "int",
          "primaryKey": false,
          "notNull": false,
          "autoincrement": false
        },
        "parkingSpots": {
          "name": "parkingSpots",
          "type": "int",
          "primaryKey": false,
          "notNull": false,
          "autoincrement": false
        },
        "suites": {
          "name": "suites",
          "type": "int",
          "primaryKey": false,
          "notNull": false,
          "autoincrement": false
        },
        "rentValue": {
          "name": "rentValue",
          "type": "decimal(12,2)",
          "primaryKey": false,
          "notNull": false,
          "autoincrement": false
        },
        "saleValue": {
          "name": "saleValue",
          "type": "decimal(14,2)",
          "primaryKey": false,
          "notNull": false,
          "autoincrement": false
        },
        "condoFee": {
          "name": "condoFee",
          "type": "decimal(10,2)",
          "primaryKey": false,
          "notNull": false,
          "autoincrement": false
        },
        "iptuValue": {
          "name": "iptuValue",
          "type": "decimal(10,2)",
          "primaryKey": false,
          "notNull": false,
          "autoincrement": false
        },
        "adminFeePercent": {
          "name": "adminFeePercent",
          "type": "decimal(5,2)",
          "primaryKey": false,
          "notNull": false,
          "autoincrement": false
        },
        "saleCommissionPercent": {
          "name": "saleCommissionPercent",
          "type": "decimal(5,2)",
          "primaryKey": false,
          "notNull": false,
          "autoincrement": false
        },
        "description": {
          "name": "description",
          "type": "text",
          "primaryKey": false,
          "notNull": false,
          "autoincrement": false
        },
        "features": {
          "name": "features",
          "type": "text",
          "primaryKey": false,
          "notNull": false,
          "autoincrement": false
        },
        "imageUrl": {
          "name": "imageUrl",
          "type": "text",
          "primaryKey": false,
          "notNull": false,
          "autoincrement": false
        },
        "createdAt": {
          "name": "createdAt",
          "type": "timestamp",
          "primaryKey": false,
          "notNull": true,
          "autoincrement": false,
          "default": "(now())"
        },
        "updatedAt": {
          "name": "updatedAt",
          "type": "timestamp",
          "primaryKey": false,
          "notNull": true,
          "autoincrement": false,
          "onUpdate": true,
          "default": "(now())"
        }
      },
      "indexes": {},
      "foreignKeys": {},
      "compositePrimaryKeys": {
        "properties_id": {
          "name": "properties_id",
          "columns": [
            "id"
          ]
        }
      },
      "uniqueConstraints": {},
      "checkConstraint": {}
    },
    "property_checklists": {
      "name": "property_checklists",
      "columns": {
        "id": {
          "name": "id",
          "type": "int",
          "primaryKey": false,
          "notNull": true,
          "autoincrement": true
        },
        "propertyId": {
          "name": "propertyId",
          "type": "int",
          "primaryKey": false,
          "notNull": true,
          "autoincrement": false
        },
        "month": {
          "name": "month",
          "type": "int",
          "primaryKey": false,
          "notNull": true,
          "autoincrement": false
        },
        "year": {
          "name": "year",
          "type": "int",
          "primaryKey": false,
          "notNull": true,
          "autoincrement": false
        },
        "item": {
          "name": "item",
          "type": "varchar(255)",
          "primaryKey": false,
          "notNull": true,
          "autoincrement": false
        },
        "isChecked": {
          "name": "isChecked",
          "type": "boolean",
          "primaryKey": false,
          "notNull": false,
          "autoincrement": false,
          "default": false
        },
        "notes": {
          "name": "notes",
          "type": "text",
          "primaryKey": false,
          "notNull": false,
          "autoincrement": false
        },
        "checkedBy": {
          "name": "checkedBy",
          "type": "int",
          "primaryKey": false,
          "notNull": false,
          "autoincrement": false
        },
        "checkedAt": {
          "name": "checkedAt",
          "type": "timestamp",
          "primaryKey": false,
          "notNull": false,
          "autoincrement": false
        },
        "createdAt": {
          "name": "createdAt",
          "type": "timestamp",
          "primaryKey": false,
          "notNull": true,
          "autoincrement": false,
          "default": "(now())"
        }
      },
      "indexes": {},
      "foreignKeys": {},
      "compositePrimaryKeys": {
        "property_checklists_id": {
          "name": "property_checklists_id",
          "columns": [
            "id"
          ]
        }
      },
      "uniqueConstraints": {},
      "checkConstraint": {}
    },
    "property_todos": {
      "name": "property_todos",
      "columns": {
        "id": {
          "name": "id",
          "type": "int",
          "primaryKey": false,
          "notNull": true,
          "autoincrement": true
        },
        "title": {
          "name": "title",
          "type": "varchar(255)",
          "primaryKey": false,
          "notNull": true,
          "autoincrement": false
        },
        "description": {
          "name": "description",
          "type": "text",
          "primaryKey": false,
          "notNull": false,
          "autoincrement": false
        },
        "propertyId": {
          "name": "propertyId",
          "type": "int",
          "primaryKey": false,
          "notNull": false,
          "autoincrement": false
        },
        "dueDate": {
          "name": "dueDate",
          "type": "date",
          "primaryKey": false,
          "notNull": false,
          "autoincrement": false
        },
        "priority": {
          "name": "priority",
          "type": "enum('baixa','media','alta')",
          "primaryKey": false,
          "notNull": true,
          "autoincrement": false,
          "default": "'media'"
        },
        "isCompleted": {
          "name": "isCompleted",
          "type": "boolean",
          "primaryKey": false,
          "notNull": false,
          "autoincrement": false,
          "default": false
        },
        "createdBy": {
          "name": "createdBy",
          "type": "int",
          "primaryKey": false,
          "notNull": false,
          "autoincrement": false
        },
        "createdAt": {
          "name": "createdAt",
          "type": "timestamp",
          "primaryKey": false,
          "notNull": true,
          "autoincrement": false,
          "default": "(now())"
        },
        "updatedAt": {
          "name": "updatedAt",
          "type": "timestamp",
          "primaryKey": false,
          "notNull": true,
          "autoincrement": false,
          "onUpdate": true,
          "default": "(now())"
        }
      },
      "indexes": {},
      "foreignKeys": {},
      "compositePrimaryKeys": {
        "property_todos_id": {
          "name": "property_todos_id",
          "columns": [
            "id"
          ]
        }
      },
      "uniqueConstraints": {},
      "checkConstraint": {}
    },
    "rental_contracts": {
      "name": "rental_contracts",
      "columns": {
        "id": {
          "name": "id",
          "type": "int",
          "primaryKey": false,
          "notNull": true,
          "autoincrement": true
        },
        "propertyId": {
          "name": "propertyId",
          "type": "int",
          "primaryKey": false,
          "notNull": true,
          "autoincrement": false
        },
        "tenantId": {
          "name": "tenantId",
          "type": "int",
          "primaryKey": false,
          "notNull": true,
          "autoincrement": false
        },
        "occupantName": {
          "name": "occupantName",
          "type": "varchar(255)",
          "primaryKey": false,
          "notNull": false,
          "autoincrement": false
        },
        "occupantCpf": {
          "name": "occupantCpf",
          "type": "varchar(14)",
          "primaryKey": false,
          "notNull": false,
          "autoincrement": false
        },
        "startDate": {
          "name": "startDate",
          "type": "date",
          "primaryKey": false,
          "notNull": true,
          "autoincrement": false
        },
        "endDate": {
          "name": "endDate",
          "type": "date",
          "primaryKey": false,
          "notNull": false,
          "autoincrement": false
        },
        "leaseTerm": {
          "name": "leaseTerm",
          "type": "enum('quinzenal','mensal','trimestral','semestral','anual','2_anos','3_anos')",
          "primaryKey": false,
          "notNull": true,
          "autoincrement": false,
          "default": "'anual'"
        },
        "rentAmount": {
          "name": "rentAmount",
          "type": "decimal(12,2)",
          "primaryKey": false,
          "notNull": true,
          "autoincrement": false
        },
        "condoIncluded": {
          "name": "condoIncluded",
          "type": "boolean",
          "primaryKey": false,
          "notNull": false,
          "autoincrement": false,
          "default": false
        },
        "iptuIncluded": {
          "name": "iptuIncluded",
          "type": "boolean",
          "primaryKey": false,
          "notNull": false,
          "autoincrement": false,
          "default": false
        },
        "isPackage": {
          "name": "isPackage",
          "type": "boolean",
          "primaryKey": false,
          "notNull": false,
          "autoincrement": false,
          "default": false
        },
        "packageTotal": {
          "name": "packageTotal",
          "type": "decimal(12,2)",
          "primaryKey": false,
          "notNull": false,
          "autoincrement": false
        },
        "adjustmentIndex": {
          "name": "adjustmentIndex",
          "type": "enum('igpm','ipca','inpc','nenhum')",
          "primaryKey": false,
          "notNull": true,
          "autoincrement": false,
          "default": "'igpm'"
        },
        "adjustmentValue": {
          "name": "adjustmentValue",
          "type": "decimal(12,2)",
          "primaryKey": false,
          "notNull": false,
          "autoincrement": false
        },
        "nextAdjustmentDate": {
          "name": "nextAdjustmentDate",
          "type": "date",
          "primaryKey": false,
          "notNull": false,
          "autoincrement": false
        },
        "billingDay": {
          "name": "billingDay",
          "type": "int",
          "primaryKey": false,
          "notNull": false,
          "autoincrement": false,
          "default": 10
        },
        "lateFeePercent": {
          "name": "lateFeePercent",
          "type": "decimal(5,2)",
          "primaryKey": false,
          "notNull": false,
          "autoincrement": false,
          "default": "'2.00'"
        },
        "dailyInterestPercent": {
          "name": "dailyInterestPercent",
          "type": "decimal(5,4)",
          "primaryKey": false,
          "notNull": false,
          "autoincrement": false,
          "default": "'0.0333'"
        },
        "contractFileUrl": {
          "name": "contractFileUrl",
          "type": "text",
          "primaryKey": false,
          "notNull": false,
          "autoincrement": false
        },
        "contractFileKey": {
          "name": "contractFileKey",
          "type": "varchar(512)",
          "primaryKey": false,
          "notNull": false,
          "autoincrement": false
        },
        "contractFileName": {
          "name": "contractFileName",
          "type": "varchar(255)",
          "primaryKey": false,
          "notNull": false,
          "autoincrement": false
        },
        "contractStatus": {
          "name": "contractStatus",
          "type": "enum('ativo','encerrado','pendente','rescindido')",
          "primaryKey": false,
          "notNull": true,
          "autoincrement": false,
          "default": "'ativo'"
        },
        "notes": {
          "name": "notes",
          "type": "text",
          "primaryKey": false,
          "notNull": false,
          "autoincrement": false
        },
        "createdAt": {
          "name": "createdAt",
          "type": "timestamp",
          "primaryKey": false,
          "notNull": true,
          "autoincrement": false,
          "default": "(now())"
        },
        "updatedAt": {
          "name": "updatedAt",
          "type": "timestamp",
          "primaryKey": false,
          "notNull": true,
          "autoincrement": false,
          "onUpdate": true,
          "default": "(now())"
        }
      },
      "indexes": {},
      "foreignKeys": {},
      "compositePrimaryKeys": {
        "rental_contracts_id": {
          "name": "rental_contracts_id",
          "columns": [
            "id"
          ]
        }
      },
      "uniqueConstraints": {},
      "checkConstraint": {}
    },
    "supplies": {
      "name": "supplies",
      "columns": {
        "id": {
          "name": "id",
          "type": "int",
          "primaryKey": false,
          "notNull": true,
          "autoincrement": true
        },
        "name": {
          "name": "name",
          "type": "varchar(255)",
          "primaryKey": false,
          "notNull": true,
          "autoincrement": false
        },
        "category": {
          "name": "category",
          "type": "enum('escritorio','copa','limpeza','outro')",
          "primaryKey": false,
          "notNull": true,
          "autoincrement": false,
          "default": "'outro'"
        },
        "currentStock": {
          "name": "currentStock",
          "type": "int",
          "primaryKey": false,
          "notNull": false,
          "autoincrement": false,
          "default": 0
        },
        "minStock": {
          "name": "minStock",
          "type": "int",
          "primaryKey": false,
          "notNull": false,
          "autoincrement": false,
          "default": 5
        },
        "unit": {
          "name": "unit",
          "type": "varchar(32)",
          "primaryKey": false,
          "notNull": false,
          "autoincrement": false,
          "default": "'un'"
        },
        "lastRestocked": {
          "name": "lastRestocked",
          "type": "date",
          "primaryKey": false,
          "notNull": false,
          "autoincrement": false
        },
        "createdAt": {
          "name": "createdAt",
          "type": "timestamp",
          "primaryKey": false,
          "notNull": true,
          "autoincrement": false,
          "default": "(now())"
        },
        "updatedAt": {
          "name": "updatedAt",
          "type": "timestamp",
          "primaryKey": false,
          "notNull": true,
          "autoincrement": false,
          "onUpdate": true,
          "default": "(now())"
        }
      },
      "indexes": {},
      "foreignKeys": {},
      "compositePrimaryKeys": {
        "supplies_id": {
          "name": "supplies_id",
          "columns": [
            "id"
          ]
        }
      },
      "uniqueConstraints": {},
      "checkConstraint": {}
    },
    "tickets": {
      "name": "tickets",
      "columns": {
        "id": {
          "name": "id",
          "type": "int",
          "primaryKey": false,
          "notNull": true,
          "autoincrement": true
        },
        "title": {
          "name": "title",
          "type": "varchar(255)",
          "primaryKey": false,
          "notNull": true,
          "autoincrement": false
        },
        "description": {
          "name": "description",
          "type": "text",
          "primaryKey": false,
          "notNull": false,
          "autoincrement": false
        },
        "category": {
          "name": "category",
          "type": "enum('ti','manutencao','limpeza','seguranca','outro')",
          "primaryKey": false,
          "notNull": true,
          "autoincrement": false,
          "default": "'outro'"
        },
        "priority": {
          "name": "priority",
          "type": "enum('baixa','media','alta','urgente')",
          "primaryKey": false,
          "notNull": true,
          "autoincrement": false,
          "default": "'media'"
        },
        "status": {
          "name": "status",
          "type": "enum('aberto','em_andamento','resolvido','fechado')",
          "primaryKey": false,
          "notNull": true,
          "autoincrement": false,
          "default": "'aberto'"
        },
        "requestedBy": {
          "name": "requestedBy",
          "type": "int",
          "primaryKey": false,
          "notNull": false,
          "autoincrement": false
        },
        "assignedTo": {
          "name": "assignedTo",
          "type": "varchar(255)",
          "primaryKey": false,
          "notNull": false,
          "autoincrement": false
        },
        "resolvedAt": {
          "name": "resolvedAt",
          "type": "timestamp",
          "primaryKey": false,
          "notNull": false,
          "autoincrement": false
        },
        "createdAt": {
          "name": "createdAt",
          "type": "timestamp",
          "primaryKey": false,
          "notNull": true,
          "autoincrement": false,
          "default": "(now())"
        },
        "updatedAt": {
          "name": "updatedAt",
          "type": "timestamp",
          "primaryKey": false,
          "notNull": true,
          "autoincrement": false,
          "onUpdate": true,
          "default": "(now())"
        }
      },
      "indexes": {},
      "foreignKeys": {},
      "compositePrimaryKeys": {
        "tickets_id": {
          "name": "tickets_id",
          "columns": [
            "id"
          ]
        }
      },
      "uniqueConstraints": {},
      "checkConstraint": {}
    },
    "time_off": {
      "name": "time_off",
      "columns": {
        "id": {
          "name": "id",
          "type": "int",
          "primaryKey": false,
          "notNull": true,
          "autoincrement": true
        },
        "employeeId": {
          "name": "employeeId",
          "type": "int",
          "primaryKey": false,
          "notNull": true,
          "autoincrement": false
        },
        "type": {
          "name": "type",
          "type": "enum('ferias','falta_justificada','falta_injustificada','licenca','outro')",
          "primaryKey": false,
          "notNull": true,
          "autoincrement": false
        },
        "startDate": {
          "name": "startDate",
          "type": "date",
          "primaryKey": false,
          "notNull": true,
          "autoincrement": false
        },
        "endDate": {
          "name": "endDate",
          "type": "date",
          "primaryKey": false,
          "notNull": true,
          "autoincrement": false
        },
        "reason": {
          "name": "reason",
          "type": "text",
          "primaryKey": false,
          "notNull": false,
          "autoincrement": false
        },
        "approved": {
          "name": "approved",
          "type": "boolean",
          "primaryKey": false,
          "notNull": false,
          "autoincrement": false,
          "default": false
        },
        "createdAt": {
          "name": "createdAt",
          "type": "timestamp",
          "primaryKey": false,
          "notNull": true,
          "autoincrement": false,
          "default": "(now())"
        }
      },
      "indexes": {},
      "foreignKeys": {},
      "compositePrimaryKeys": {
        "time_off_id": {
          "name": "time_off_id",
          "columns": [
            "id"
          ]
        }
      },
      "uniqueConstraints": {},
      "checkConstraint": {}
    },
    "users": {
      "name": "users",
      "columns": {
        "id": {
          "name": "id",
          "type": "int",
          "primaryKey": false,
          "notNull": true,
          "autoincrement": true
        },
        "openId": {
          "name": "openId",
          "type": "varchar(64)",
          "primaryKey": false,
          "notNull": true,
          "autoincrement": false
        },
        "name": {
          "name": "name",
          "type": "text",
          "primaryKey": false,
          "notNull": false,
          "autoincrement": false
        },
        "email": {
          "name": "email",
          "type": "varchar(320)",
          "primaryKey": false,
          "notNull": false,
          "autoincrement": false
        },
        "loginMethod": {
          "name": "loginMethod",
          "type": "varchar(64)",
          "primaryKey": false,
          "notNull": false,
          "autoincrement": false
        },
        "role": {
          "name": "role",
          "type": "enum('admin','gerente','operador')",
          "primaryKey": false,
          "notNull": true,
          "autoincrement": false,
          "default": "'operador'"
        },
        "createdAt": {
          "name": "createdAt",
          "type": "timestamp",
          "primaryKey": false,
          "notNull": true,
          "autoincrement": false,
          "default": "(now())"
        },
        "updatedAt": {
          "name": "updatedAt",
          "type": "timestamp",
          "primaryKey": false,
          "notNull": true,
          "autoincrement": false,
          "onUpdate": true,
          "default": "(now())"
        },
        "lastSignedIn": {
          "name": "lastSignedIn",
          "type": "timestamp",
          "primaryKey": false,
          "notNull": true,
          "autoincrement": false,
          "default": "(now())"
        }
      },
      "indexes": {},
      "foreignKeys": {},
      "compositePrimaryKeys": {
        "users_id": {
          "name": "users_id",
          "columns": [
            "id"
          ]
        }
      },
      "uniqueConstraints": {
        "users_openId_unique": {
          "name": "users_openId_unique",
          "columns": [
            "openId"
          ]
        }
      },
      "checkConstraint": {}
    },
    "viabilidade": {
      "name": "viabilidade",
      "columns": {
        "id": {
          "name": "id",
          "type": "int",
          "primaryKey": false,
          "notNull": true,
          "autoincrement": true
        },
        "negocioId": {
          "name": "negocioId",
          "type": "int",
          "primaryKey": false,
          "notNull": true,
          "autoincrement": false
        },
        "landCost": {
          "name": "landCost",
          "type": "decimal(14,2)",
          "primaryKey": false,
          "notNull": false,
          "autoincrement": false,
          "default": "'0'"
        },
        "constructionCost": {
          "name": "constructionCost",
          "type": "decimal(14,2)",
          "primaryKey": false,
          "notNull": false,
          "autoincrement": false,
          "default": "'0'"
        },
        "indirectCosts": {
          "name": "indirectCosts",
          "type": "decimal(14,2)",
          "primaryKey": false,
          "notNull": false,
          "autoincrement": false,
          "default": "'0'"
        },
        "taxes": {
          "name": "taxes",
          "type": "decimal(14,2)",
          "primaryKey": false,
          "notNull": false,
          "autoincrement": false,
          "default": "'0'"
        },
        "commissions": {
          "name": "commissions",
          "type": "decimal(14,2)",
          "primaryKey": false,
          "notNull": false,
          "autoincrement": false,
          "default": "'0'"
        },
        "totalCost": {
          "name": "totalCost",
          "type": "decimal(14,2)",
          "primaryKey": false,
          "notNull": false,
          "autoincrement": false
        },
        "netProfit": {
          "name": "netProfit",
          "type": "decimal(14,2)",
          "primaryKey": false,
          "notNull": false,
          "autoincrement": false
        },
        "profitMargin": {
          "name": "profitMargin",
          "type": "decimal(8,2)",
          "primaryKey": false,
          "notNull": false,
          "autoincrement": false
        },
        "tir": {
          "name": "tir",
          "type": "decimal(8,2)",
          "primaryKey": false,
          "notNull": false,
          "autoincrement": false
        },
        "roi": {
          "name": "roi",
          "type": "decimal(8,2)",
          "primaryKey": false,
          "notNull": false,
          "autoincrement": false
        },
        "viabilityStatus": {
          "name": "viabilityStatus",
          "type": "enum('verde','amarelo','vermelho')",
          "primaryKey": false,
          "notNull": false,
          "autoincrement": false,
          "default": "'amarelo'"
        },
        "viabNotes": {
          "name": "viabNotes",
          "type": "text",
          "primaryKey": false,
          "notNull": false,
          "autoincrement": false
        },
        "createdAt": {
          "name": "createdAt",
          "type": "timestamp",
          "primaryKey": false,
          "notNull": true,
          "autoincrement": false,
          "default": "(now())"
        },
        "updatedAt": {
          "name": "updatedAt",
          "type": "timestamp",
          "primaryKey": false,
          "notNull": true,
          "autoincrement": false,
          "onUpdate": true,
          "default": "(now())"
        }
      },
      "indexes": {},
      "foreignKeys": {},
      "compositePrimaryKeys": {
        "viabilidade_id": {
          "name": "viabilidade_id",
          "columns": [
            "id"
          ]
        }
      },
      "uniqueConstraints": {},
      "checkConstraint": {}
    }
  },
  "views": {},
  "_meta": {
    "schemas": {},
    "tables": {},
    "columns": {}
  },
  "internal": {
    "tables": {},
    "indexes": {}
  }
}